<annotation>
	<folder>front</folder>
	<filename>Image_20220901183557902.jpg</filename>
	<path>D:\02_workSpace\code\02_yangfeng\dataset\train_data\linestyle\front\Image_20220901183557902.jpg</path>
	<source>
		<database>Unknown</database>
	</source>
	<size>
		<width>2592</width>
		<height>2048</height>
		<depth>3</depth>
	</size>
	<segmented>0</segmented>
	<object>
		<name>vline</name>
		<pose>Unspecified</pose>
		<truncated>0</truncated>
		<difficult>0</difficult>
		<bndbox>
			<xmin>649</xmin>
			<ymin>1430</ymin>
			<xmax>666</xmax>
			<ymax>1495</ymax>
		</bndbox>
	</object>
	<object>
		<name>vline</name>
		<pose>Unspecified</pose>
		<truncated>0</truncated>
		<difficult>0</difficult>
		<bndbox>
			<xmin>641</xmin>
			<ymin>1497</ymin>
			<xmax>664</xmax>
			<ymax>1564</ymax>
		</bndbox>
	</object>
	<object>
		<name>vline</name>
		<pose>Unspecified</pose>
		<truncated>0</truncated>
		<difficult>0</difficult>
		<bndbox>
			<xmin>635</xmin>
			<ymin>1567</ymin>
			<xmax>652</xmax>
			<ymax>1611</ymax>
		</bndbox>
	</object>
</annotation>
